whitecanvas/__init__.py
whitecanvas/_axis.py
whitecanvas/_exceptions.py
whitecanvas/_json_utils.py
whitecanvas/_signal.py
whitecanvas/animation.py
whitecanvas/core.py
whitecanvas/backend/__init__.py
whitecanvas/backend/_app.py
whitecanvas/backend/_instance.py
whitecanvas/backend/_not_implemented.py
whitecanvas/backend/_window/__init__.py
whitecanvas/backend/_window/_qt.py
whitecanvas/backend/_window/_tk.py
whitecanvas/backend/bokeh/__init__.py
whitecanvas/backend/bokeh/_base.py
whitecanvas/backend/bokeh/_labels.py
whitecanvas/backend/bokeh/_legend.py
whitecanvas/backend/bokeh/band.py
whitecanvas/backend/bokeh/bars.py
whitecanvas/backend/bokeh/canvas.py
whitecanvas/backend/bokeh/image.py
whitecanvas/backend/bokeh/line.py
whitecanvas/backend/bokeh/markers.py
whitecanvas/backend/bokeh/text.py
whitecanvas/backend/matplotlib/__init__.py
whitecanvas/backend/matplotlib/_base.py
whitecanvas/backend/matplotlib/_labels.py
whitecanvas/backend/matplotlib/_legend.py
whitecanvas/backend/matplotlib/band.py
whitecanvas/backend/matplotlib/bars.py
whitecanvas/backend/matplotlib/canvas.py
whitecanvas/backend/matplotlib/image.py
whitecanvas/backend/matplotlib/line.py
whitecanvas/backend/matplotlib/markers.py
whitecanvas/backend/matplotlib/text.py
whitecanvas/backend/matplotlib/vectors.py
whitecanvas/backend/matplotlib/components3d/__init__.py
whitecanvas/backend/matplotlib/components3d/canvas.py
whitecanvas/backend/matplotlib/components3d/line.py
whitecanvas/backend/matplotlib/components3d/markers.py
whitecanvas/backend/matplotlib/components3d/mesh.py
whitecanvas/backend/matplotlib/components3d/vectors3d.py
whitecanvas/backend/mock/__init__.py
whitecanvas/backend/mock/_base.py
whitecanvas/backend/mock/canvas.py
whitecanvas/backend/mock/layers.py
whitecanvas/backend/plotly/__init__.py
whitecanvas/backend/plotly/_base.py
whitecanvas/backend/plotly/_labels.py
whitecanvas/backend/plotly/_legend.py
whitecanvas/backend/plotly/band.py
whitecanvas/backend/plotly/bars.py
whitecanvas-0.3.4.dist-info/METADATA
whitecanvas-0.3.4.dist-info/WHEEL
whitecanvas-0.3.4.dist-info/licenses/LICENSE
whitecanvas-0.3.4.dist-info/RECORD
