Metadata-Version: 2.4
Name: whitecanvas
Version: 0.3.4
Summary: A type safe and backend independent plotting library for Python.
Project-URL: Documentation, https://github.com/hanjinliu/whitecanvas#readme
Project-URL: Issues, https://github.com/hanjinliu/whitecanvas/issues
Project-URL: Source, https://github.com/hanjinliu/whitecanvas
Author-email: Hanjin Liu <liuhanjin-sc@g.ecc.u-tokyo.ac.jp>
License: BSD 3-Clause License
License-File: LICENSE
Classifier: Development Status :: 4 - Beta
Classifier: Programming Language :: Python
Classifier: Programming Language :: Python :: 3.9
Classifier: Programming Language :: Python :: 3.10
Classifier: Programming Language :: Python :: 3.11
Classifier: Programming Language :: Python :: 3.12
Classifier: Programming Language :: Python :: 3.13
Classifier: Programming Language :: Python :: Implementation :: CPython
Classifier: Programming Language :: Python :: Implementation :: PyPy
Requires-Python: >=3.9
Requires-Dist: cmap>=0.3.0
Requires-Dist: numpy>=1.23.2
Requires-Dist: platformdirs
Requires-Dist: psygnal!=0.10.0,>=0.9.4
Requires-Dist: typing-extensions>=4.5.0
Provides-Extra: bokeh
Requires-Dist: bokeh>=3.3.1; extra == 'bokeh'
Provides-Extra: docs
Requires-Dist: imageio>=2.9.0; extra == 'docs'
Requires-Dist: matplotlib>=3.8.2; extra == 'docs'
Requires-Dist: mkdocs; extra == 'docs'
Requires-Dist: mkdocs-autorefs==1.0.1; extra == 'docs'
Requires-Dist: mkdocs-gen-files; extra == 'docs'
Requires-Dist: mkdocs-material-extensions==1.3.1; extra == 'docs'
Requires-Dist: mkdocs-material==9.5.23; extra == 'docs'
Requires-Dist: mkdocstrings-python==1.10.8; extra == 'docs'
Requires-Dist: mkdocstrings==0.25.2; extra == 'docs'
Requires-Dist: plotly>=5.3.1; extra == 'docs'
Requires-Dist: statsmodels>=0.13.0; extra == 'docs'
Provides-Extra: matplotlib
Requires-Dist: matplotlib!=3.8.0,>=3.4.3; extra == 'matplotlib'
Provides-Extra: plotly
Requires-Dist: kaleido>=0.2.1; extra == 'plotly'
Requires-Dist: plotly>=5.3.1; extra == 'plotly'
Provides-Extra: pyqtgraph
Requires-Dist: pyqtgraph>=0.13.3; extra == 'pyqtgraph'
Requires-Dist: qtpy>=2.4.1; extra == 'pyqtgraph'
Provides-Extra: testing
Requires-Dist: bokeh>=3.3.1; extra == 'testing'
Requires-Dist: imageio; extra == 'testing'
Requires-Dist: ipywidgets>=8.0.0; extra == 'testing'
Requires-Dist: matplotlib>=3.8.2; extra == 'testing'
Requires-Dist: pandas>=1.3.3; extra == 'testing'
Requires-Dist: plotly>=5.3.1; extra == 'testing'
Requires-Dist: polars>=0.20.10; extra == 'testing'
Requires-Dist: pyqt5>=5.15.4; extra == 'testing'
Requires-Dist: pyqtgraph>=0.13.3; extra == 'testing'
Requires-Dist: pytest; extra == 'testing'
Requires-Dist: pytest-cov; extra == 'testing'
Requires-Dist: pytest-qt; extra == 'testing'
Requires-Dist: qtpy>=2.4.1; extra == 'testing'
Requires-Dist: statsmodels>=0.13.0; extra == 'testing'
Requires-Dist: vispy>=0.14.2; extra == 'testing'
Provides-Extra: vispy
Requires-Dist: vispy>=0.14.2; extra == 'vispy'
